lwalkm/__init__.py
lwalkm/pipeline.py
lwalkm_simura_works-0.1.7.dist-info/LICENSE
lwalkm_simura_works-0.1.7.dist-info/METADATA
lwalkm_simura_works-0.1.7.dist-info/WHEEL
lwalkm_simura_works-0.1.7.dist-info/top_level.txt
lwalkm_simura_works-0.1.7.dist-info/RECORD
