Metadata-Version: 2.2
Name: lwalkm_simura-works
Version: 0.1.7
Summary: Integrated Protein Morphing Pipeline with GROMACS and CorrectionNet
Home-page: https://github.com/simura-works/lwalkm_simura-works
Author: Bernard Essuman
Author-email: Bernard Essuman <bessuman.academia@gmail.com>
License: MIT License
Project-URL: Homepage, https://github.com/simura-works/lwalkm_simura-works
Project-URL: Issues, https://github.com/simura-works/lwalkm_simura-works/issues
Classifier: Programming Language :: Python :: 3
Classifier: Operating System :: OS Independent
Classifier: License :: OSI Approved :: MIT License
Classifier: Development Status :: 4 - Beta
Classifier: Intended Audience :: Science/Research
Classifier: Topic :: Scientific/Engineering :: Bio-Informatics
Requires-Python: >=3.8
License-File: LICENSE
